conflowgen/__init__.py
conflowgen/metadata.py
conflowgen/analyses/__init__.py
conflowgen/analyses/abstract_analysis.py
conflowgen/analyses/container_dwell_time_analysis.py
conflowgen/analyses/container_dwell_time_analysis_report.py
conflowgen/analyses/container_flow_adjustment_by_vehicle_type_analysis.py
conflowgen/analyses/container_flow_adjustment_by_vehicle_type_analysis_report.py
conflowgen/analyses/container_flow_adjustment_by_vehicle_type_analysis_summary.py
conflowgen/analyses/container_flow_adjustment_by_vehicle_type_analysis_summary_report.py
conflowgen/analyses/container_flow_by_vehicle_instance_analysis.py
conflowgen/analyses/container_flow_by_vehicle_instance_analysis_report.py
conflowgen/analyses/container_flow_by_vehicle_type_analysis.py
conflowgen/analyses/container_flow_by_vehicle_type_analysis_report.py
conflowgen/analyses/container_flow_vehicle_type_adjustment_per_vehicle_analysis.py
conflowgen/analyses/container_flow_vehicle_type_adjustment_per_vehicle_analysis_report.py
conflowgen/analyses/inbound_and_outbound_vehicle_capacity_analysis.py
conflowgen/analyses/inbound_and_outbound_vehicle_capacity_analysis_report.py
conflowgen/analyses/modal_split_analysis.py
conflowgen/analyses/modal_split_analysis_report.py
conflowgen/analyses/outbound_to_inbound_vehicle_capacity_utilization_analysis.py
conflowgen/analyses/outbound_to_inbound_vehicle_capacity_utilization_analysis_report.py
conflowgen/analyses/quay_side_throughput_analysis.py
conflowgen/analyses/quay_side_throughput_analysis_report.py
conflowgen/analyses/truck_gate_throughput_analysis.py
conflowgen/analyses/truck_gate_throughput_analysis_report.py
conflowgen/analyses/yard_capacity_analysis.py
conflowgen/analyses/yard_capacity_analysis_report.py
conflowgen/api/__init__.py
conflowgen/api/container_dwell_time_distribution_manager.py
conflowgen/api/container_flow_generation_manager.py
conflowgen/api/container_length_distribution_manager.py
conflowgen/api/container_weight_distribution_manager.py
conflowgen-3.0.1.dist-info/licenses/LICENSE
conflowgen-3.0.1.dist-info/METADATA
conflowgen-3.0.1.dist-info/WHEEL
conflowgen-3.0.1.dist-info/top_level.txt
conflowgen-3.0.1.dist-info/RECORD
