Metadata-Version: 2.4
Name: conflowgen
Version: 3.0.1
Summary: A generator for synthetic container flows at maritime container terminals with a focus on yard operations
Home-page: https://github.com/1kastner/conflowgen
Author: Marvin Kastner, Ole Grasse, and Shubhangi Gupta
Author-email: Marvin Kastner <marvin.kastner@tuhh.de>
License: MIT
Requires-Python: >=3.9
License-File: LICENSE
Requires-Dist: scipy>=1.10.0-rc1
Requires-Dist: numpy
Requires-Dist: pandas>=1
Requires-Dist: openpyxl
Requires-Dist: peewee>=3
Requires-Dist: enum_tools>=0.7
Requires-Dist: matplotlib
Requires-Dist: plotly
Requires-Dist: kaleido>=1.0
Provides-Extra: dev
Requires-Dist: pytest; extra == "dev"
Requires-Dist: pytest-cov; extra == "dev"
Requires-Dist: pytest-xdist; extra == "dev"
Requires-Dist: pytest-github-actions-annotate-failures; extra == "dev"
Requires-Dist: parameterized; extra == "dev"
Requires-Dist: seaborn; extra == "dev"
Requires-Dist: nbconvert; extra == "dev"
Requires-Dist: nbformat; extra == "dev"
Requires-Dist: sphinx>=6.2; extra == "dev"
Requires-Dist: sphinx-rtd-theme; extra == "dev"
Requires-Dist: sphinx-toolbox>=3; extra == "dev"
Requires-Dist: myst-parser; extra == "dev"
Requires-Dist: sphinxcontrib-bibtex>=2.4; extra == "dev"
Requires-Dist: sphinx-last-updated-by-git; extra == "dev"
Requires-Dist: nbsphinx; extra == "dev"
Requires-Dist: ipython; extra == "dev"
Requires-Dist: ipykernel; extra == "dev"
Requires-Dist: docutils; extra == "dev"
Requires-Dist: pylint; extra == "dev"
Requires-Dist: flake8; extra == "dev"
Requires-Dist: ruff; extra == "dev"
Requires-Dist: wheel; extra == "dev"
Requires-Dist: twine; extra == "dev"
Requires-Dist: sphinx-tabs; extra == "dev"
Provides-Extra: jupyterlab
Requires-Dist: jupyterlab; extra == "jupyterlab"
Requires-Dist: jupyterlab-spellchecker; extra == "jupyterlab"
Requires-Dist: jupyterlab-lsp; extra == "jupyterlab"
Requires-Dist: python-lsp-server[all]; extra == "jupyterlab"
Dynamic: author
Dynamic: description
Dynamic: description-content-type
Dynamic: home-page
Dynamic: license
Dynamic: license-file
Dynamic: summary
